apophis/__init__.py
apophis/apophis.py
apophis/configuration.py
apophis/console.py
apophis/exchange.py
apophis-1.0.5.dist-info/entry_points.txt
apophis-1.0.5.dist-info/LICENSE
apophis-1.0.5.dist-info/WHEEL
apophis-1.0.5.dist-info/METADATA
apophis-1.0.5.dist-info/RECORD
