Metadata-Version: 2.1
Name: apophis
Version: 1.0.5
Summary: Apophis: A python client for Kraken
Home-page: https://github.com/tupui/apophis
License: MIT
Keywords: cryptocurrency,kraken,API,REST
Author: Pamphile Roy
Author-email: roy.pamphile@gmail.com
Requires-Python: >=3.8,<4.0
Classifier: License :: OSI Approved :: MIT License
Classifier: Programming Language :: Python :: 3
Classifier: Programming Language :: Python :: 3.8
Classifier: Programming Language :: Python :: 3.9
Requires-Dist: pandas (>=1.1.5,<2.0.0)
Requires-Dist: pydantic (>=1.7.2,<2.0.0)
Requires-Dist: requests (>=2.25.0,<3.0.0)
Requires-Dist: typer[all] (>=0.3.2,<0.4.0)
Project-URL: Repository, https://github.com/tupui/apophis
